hirlite/__init__.py
hirlite/hirlite.so
hirlite/version.py
hirlite-0.1.1.dist-info/DESCRIPTION.rst
hirlite-0.1.1.dist-info/METADATA
hirlite-0.1.1.dist-info/metadata.json
hirlite-0.1.1.dist-info/RECORD
hirlite-0.1.1.dist-info/top_level.txt
hirlite-0.1.1.dist-info/WHEEL
